certbot_httpreq.py
certbot_lego_httpreq-0.1.4.dist-info/LICENSE
certbot_lego_httpreq-0.1.4.dist-info/METADATA
certbot_lego_httpreq-0.1.4.dist-info/WHEEL
certbot_lego_httpreq-0.1.4.dist-info/entry_points.txt
certbot_lego_httpreq-0.1.4.dist-info/top_level.txt
certbot_lego_httpreq-0.1.4.dist-info/RECORD
