Metadata-Version: 2.1
Name: certbot-lego-httpreq
Version: 0.1.4
Summary: Certbot authenticator plugin for HTTP requests to custom endpoints.
Author-email: Cornelius Hoffmann <coding@hoffmn.de>
License: GNU GENERAL PUBLIC LICENSE
Project-URL: Homepage, https://github.com/Cornelicorn/certbot-httpreq
Project-URL: Repository, https://github.com/Cornelicorn/certbot-httpreq
Project-URL: Issues, https://github.com/Cornelicorn/certbot-httpreq/issues
License-File: LICENSE
Requires-Dist: certbot
Requires-Dist: httpx
